lodkit/__init__.py
lodkit/rdf_importer.py
lodkit/types.py
lodkit/namespace_tools/ontology_namespace.py
lodkit/triple_tools/__init__.py
lodkit/triple_tools/triple_chain.py
lodkit/triple_tools/ttl_constructor.py
lodkit/triple_tools/utils.py
lodkit/uri_tools/uri_constructor.py
lodkit-0.6.0.dist-info/METADATA
lodkit-0.6.0.dist-info/WHEEL
lodkit-0.6.0.dist-info/licenses/LICENSE
lodkit-0.6.0.dist-info/RECORD
