Metadata-Version: 2.4
Name: lodkit
Version: 0.6.0
Author-email: Lukas Plank <lupl@tuta.io>
License-File: LICENSE
Requires-Python: >=3.12
Requires-Dist: rdflib>=7.5.0
